Workbook

Sheet Cost Model
A1: ECOGO — Monthly Cloud + API Cost vs. Revenue
A2: Cloud & API only. Excludes the real cost centres: dispatcher salaries, driver incentives/CAC, support, ops.
A3: Metric (per month) | B3: Pilot | C3: Growth | D3: Scale
A4: Trips / month | B4: 100 | C4: 1000 | D4: 10000
A5: API VOLUME
A6: Billable directions calls | B6: =B4*Assumptions!$B$20*(1-Assumptions!$B$21) -> 75 | C6: =C4*Assumptions!$B$20*(1-Assumptions!$B$21) -> 750 | D6: =D4*Assumptions!$B$20*(1-Assumptions!$B$21) -> 7500
A7: Map loads | B7: =B4*Assumptions!$B$22 -> 300 | C7: =C4*Assumptions!$B$22 -> 3000 | D7: =D4*Assumptions!$B$22 -> 30000
A8: Autocomplete requests | B8: =B4*Assumptions!$B$23 -> 800 | C8: =C4*Assumptions!$B$23 -> 8000 | D8: =D4*Assumptions!$B$23 -> 80000
A9: Reverse geocoding requests | B9: =B4*Assumptions!$B$24 -> 100 | C9: =C4*Assumptions!$B$24 -> 1000 | D9: =D4*Assumptions!$B$24 -> 10000
A10: SMS OTP messages | B10: =B4*Assumptions!$B$25 -> 30 | C10: =C4*Assumptions!$B$25 -> 300 | D10: =D4*Assumptions!$B$25 -> 3000
A11: VARIABLE COST (USD)
A12: Directions | B12: =B6/1000*Assumptions!$B$8 -> 0.1875 | C12: =C6/1000*Assumptions!$B$8 -> 1.875 | D12: =D6/1000*Assumptions!$B$8 -> 18.75
A13: Map loads | B13: =B7/1000*Assumptions!$B$9 -> 0.9 | C13: =C7/1000*Assumptions!$B$9 -> 9 | D13: =D7/1000*Assumptions!$B$9 -> 90
A14: Autocomplete | B14: =B8/1000*Assumptions!$B$10 -> 1.12 | C14: =C8/1000*Assumptions!$B$10 -> 11.2 | D14: =D8/1000*Assumptions!$B$10 -> 112
A15: Reverse geocoding | B15: =B9/1000*Assumptions!$B$11 -> 0.15 | C15: =C9/1000*Assumptions!$B$11 -> 1.5 | D15: =D9/1000*Assumptions!$B$11 -> 15
A16: SMS OTP | B16: =B10*Assumptions!$B$15/Assumptions!$B$5 -> 0.46153846 | C16: =C10*Assumptions!$B$15/Assumptions!$B$5 -> 4.6153846 | D16: =D10*Assumptions!$B$15/Assumptions!$B$5 -> 46.153846
A17: Push (FCM) | B17: =Assumptions!$B$16 -> 0 | C17: =Assumptions!$B$16 -> 0 | D17: =Assumptions!$B$16 -> 0
A18: Variable subtotal | B18: =SUM(B12:B17) -> 2.8190385 | C18: =SUM(C12:C17) -> 28.190385 | D18: =SUM(D12:D17) -> 281.90385
A19: FIXED COST (USD)
A20: Cloud infra (compute, managed PG+PostGIS, Redis, bandwidth) | B20: 25 | C20: 80 | D20: 300
A21: SMS brandname upkeep | B21: =Assumptions!$B$17/Assumptions!$B$5 -> 5.7692308 | C21: =Assumptions!$B$17/Assumptions!$B$5 -> 5.7692308 | D21: =Assumptions!$B$17/Assumptions!$B$5 -> 5.7692308
A22: Fixed subtotal | B22: =B20+B21 -> 30.769231 | C22: =C20+C21 -> 85.769231 | D22: =D20+D21 -> 305.76923
A24: TOTAL COST (USD / mo) | B24: =B18+B22 -> 33.588269 | C24: =C18+C22 -> 113.95962 | D24: =D18+D22 -> 587.67308
A25: Total cost (VND / mo) | B25: =B24*Assumptions!$B$5 -> 873295 | C25: =C24*Assumptions!$B$5 -> 2962950 | D25: =D24*Assumptions!$B$5 -> 15279500
A26: Cost per trip (VND) | B26: =IF(B4=0,0,B25/B4) -> 8732.95 | C26: =IF(C4=0,0,C25/C4) -> 2962.95 | D26: =IF(D4=0,0,D25/D4) -> 1527.95
A27: REVENUE
A28: Gross fee revenue (VND) | B28: =B4*Assumptions!$B$28*Assumptions!$B$29 -> 2000000 | C28: =C4*Assumptions!$B$28*Assumptions!$B$29 -> 20000000 | D28: =D4*Assumptions!$B$28*Assumptions!$B$29 -> 200000000
A29: Affiliate payout (VND) | B29: =B4*Assumptions!$B$30*Assumptions!$B$28*Assumptions!$B$31 -> 150000 | C29: =C4*Assumptions!$B$30*Assumptions!$B$28*Assumptions!$B$31 -> 1500000 | D29: =D4*Assumptions!$B$30*Assumptions!$B$28*Assumptions!$B$31 -> 15000000
A30: Net revenue (VND) | B30: =B28-B29 -> 1850000 | C30: =C28-C29 -> 18500000 | D30: =D28-D29 -> 185000000
A31: Net revenue (USD) | B31: =B30/Assumptions!$B$5 -> 71.153846 | C31: =C30/Assumptions!$B$5 -> 711.53846 | D31: =D30/Assumptions!$B$5 -> 7115.3846
A33: CONTRIBUTION MARGIN (USD / mo) | B33: =B31-B24 -> 37.565577 | C33: =C31-C24 -> 597.57885 | D33: =D31-D24 -> 6527.7115
A34: Margin per trip (VND) | B34: =IF(B4=0,0,(B30-B25)/B4) -> 9767.05 | C34: =IF(C4=0,0,(C30-C25)/C4) -> 15537.05 | D34: =IF(D4=0,0,(D30-D25)/D4) -> 16972.05
A35: Margin % | B35: =IF(B31=0,0,(B31-B24)/B31) -> 0.52794865 | C35: =IF(C31=0,0,(C31-C24)/C31) -> 0.83984054 | D35: =IF(D31=0,0,(D31-D24)/D31) -> 0.91740811

Sheet Assumptions
A1: ECOGO — Cost Model Assumptions
A2: Blue = editable input. Prices current as of Jun 2026 — replace with your real quotes before relying on this.
A4: FX & RATES
A5: FX rate | B5: 26000 | C5: VND / USD | D5: Approx mid-2026; editable
A7: GOONG API — USD per 1,000 requests (<100k/mo tier)
A8: Directions | B8: 2.5 | C8: USD/1k | D8: Source: goong.io/pricing-plans, Jun 2026
A9: Map Loads | B9: 3 | C9: USD/1k | D9: Source: goong.io/pricing-plans, Jun 2026
A10: Autocomplete | B10: 1.4 | C10: USD/1k | D10: Source: goong.io/pricing-plans, Jun 2026
A11: Reverse Geocoding | B11: 1.5 | C11: USD/1k | D11: Source: goong.io/pricing-plans, Jun 2026
A12: Forward Geocoding | B12: 3.5 | C12: USD/1k | D12: Source: goong.io/pricing-plans, Jun 2026
A14: MESSAGING
A15: SMS OTP | B15: 400 | C15: VND / msg | D15: Source: sms-brandname.vn, Jun 2026. Zalo ZNS OTP ~300đ alt.
A16: Push (FCM) | B16: 0 | C16: USD | D16: Firebase Cloud Messaging is free
A17: SMS brandname upkeep | B17: 150000 | C17: VND / mo | D17: ~50k/carrier x 3 carriers maintenance
A19: USAGE PER COMPLETED TRIP
A20: Directions calls / trip | B20: 1.5 | C20: calls | D20: 1 per ride posted + occasional re-route/ETA
A21: Directions cache hit rate | B21: 0.5 | C21: fraction | D21: Cached corridor routes not re-billed
A22: Map loads / trip | B22: 3 | C22: loads | D22: Build uses FREE OSM tiles -> set 0 if not using Goong tiles
A23: Autocomplete reqs / trip | B23: 8 | C23: reqs | D23: MVP uses preset corridor stops -> set 0
A24: Reverse geocoding / trip | B24: 1 | C24: reqs | D24: Occasional GPS-to-label
A25: SMS OTP / trip | B25: 0.3 | C25: msgs | D25: Logins amortised (JWT lasts ~30d)
A27: REVENUE
A28: Avg fare / booking | B28: 200000 | C28: VND | D28: Editable — corridor dependent
A29: Platform fee | B29: 0.1 | C29: % of fare | D29: 10% taken from driver
A30: Referred-trip share | B30: 0.15 | C30: fraction | D30: Share of trips paying the 3-yr affiliate
A31: Affiliate rate | B31: 0.05 | C31: % of fare | D31: 5% to referring driver

Sheet Notes
A1: How to read this model
A3: Scenarios: Pilot = 100 trips/mo, Growth = 1,000, Scale = 10,000. Change any blue cell to re-scenario.
A5: What dominates the cost — and the levers:
A6: 1. Autocomplete and Map Loads are the biggest variable lines IF you wire address search and Goong map tiles.
A7: The MVP avoids both: it uses preset corridor stops (no autocomplete) and free OpenStreetMap tiles (no map-load
A8: billing). Set those usage rows to 0 to model the as-built app — variable cost then collapses to near zero.
A9: 2. Directions is cheap ($2.50/1k) and called ~once per ride; caching identical corridors trims it further.
A10: 3. SMS OTP is per login, not per trip; amortised it is a few hundred dong per trip. Zalo ZNS OTP (300đ) is cheaper.
A11: 4. Push (FCM) is free.
A13: Unit economics: a 10% fee on a ~200,000đ fare is ~20,000đ/trip of revenue, while cloud+API cost per trip is on the
A14: order of a few hundred to ~3,000đ. The technology is NOT the constraint on margin at any of these volumes.
A16: What this model excludes (the real P&L drivers):
... A24: All prices are estimates as of Jun 2026 from public pricing pages. Replace with contracted quotes before budgeting.
