Workbook

Sheet P&L Model
A1: ECOGO — Monthly Operating P&L & Break-even
A2: Full operating view: revenue vs. tech + acquisition + staffing + overhead. This is the real go/no-go picture.
A3: Line (per month) | B3: Pilot | C3: Growth | D3: Scale
A4: Trips / month | B4: 100 | C4: 1000 | D4: 10000
A5: REVENUE
A6: Platform fee revenue | B6: =B4*Assumptions!$B$5*Assumptions!$B$6 -> 2000000 | C6: =C4*Assumptions!$B$5*Assumptions!$B$6 -> 20000000 | D6: =D4*Assumptions!$B$5*Assumptions!$B$6 -> 200000000
A7: VARIABLE COST
A8: Technology (cloud + API) | B8: =B4*Assumptions!$B$9 -> 200000 | C8: =C4*Assumptions!$B$9 -> 2000000 | D8: =D4*Assumptions!$B$9 -> 20000000
A9: Affiliate payout (5% / 3yr) | B9: =B4*Assumptions!$B$11*Assumptions!$B$5*Assumptions!$B$12 -> 150000 | C9: =C4*Assumptions!$B$11*Assumptions!$B$5*Assumptions!$B$12 -> 1500000 | D9: =D4*Assumptions!$B$11*Assumptions!$B$5*Assumptions!$B$12 -> 15000000
A10: Marketing / incentives | B10: =B4*Assumptions!$B$13 -> 500000 | C10: =C4*Assumptions!$B$13 -> 5000000 | D10: =D4*Assumptions!$B$13 -> 50000000
A11: Driver CAC (amortised) | B11: =B4*(Assumptions!$B$16/(Assumptions!$B$17*Assumptions!$B$18)) -> 125000 | C11: =C4*(Assumptions!$B$16/(Assumptions!$B$17*Assumptions!$B$18)) -> 1250000 | D11: =D4*(Assumptions!$B$16/(Assumptions!$B$17*Assumptions!$B$18)) -> 12500000
A12: Variable subtotal | B12: =SUM(B8:B11) -> 975000 | C12: =SUM(C8:C11) -> 9750000 | D12: =SUM(D8:D11) -> 97500000
A13: Contribution margin | B13: =B6-B12 -> 1025000 | C13: =C6-C12 -> 10250000 | D13: =D6-D12 -> 102500000
A14: Contribution per trip | B14: =IF(B4=0,0,B13/B4) -> 10250 | C14: =IF(C4=0,0,C13/C4) -> 10250 | D14: =IF(D4=0,0,D13/D4) -> 10250
A15: FIXED COST
A16: Dispatchers needed (count) | B16: =MAX(Assumptions!$B$23,CEILING(B4*(1-Assumptions!$B$10)/Assumptions!$B$22,1)) -> 1 | C16: =MAX(Assumptions!$B$23,CEILING(C4*(1-Assumptions!$B$10)/Assumptions!$B$22,1)) -> 1 | D16: =MAX(Assumptions!$B$23,CEILING(D4*(1-Assumptions!$B$10)/Assumptions!$B$22,1)) -> 2
A17: Dispatcher cost | B17: =B16*Assumptions!$B$21 -> 12000000 | C17: =C16*Assumptions!$B$21 -> 12000000 | D17: =D16*Assumptions!$B$21 -> 24000000
A18: Support agents needed (count) | B18: =CEILING(B4/Assumptions!$B$25,1) -> 1 | C18: =CEILING(C4/Assumptions!$B$25,1) -> 1 | D18: =CEILING(D4/Assumptions!$B$25,1) -> 2
A19: Support cost | B19: =B18*Assumptions!$B$24 -> 10000000 | C19: =C18*Assumptions!$B$24 -> 10000000 | D19: =D18*Assumptions!$B$24 -> 20000000
A20: Overhead | B20: =Assumptions!$B$26 -> 15000000 | C20: =Assumptions!$B$26 -> 15000000 | D20: =Assumptions!$B$26 -> 15000000
A21: Brandname upkeep | B21: =Assumptions!$B$27 -> 150000 | C21: =Assumptions!$B$27 -> 150000 | D21: =Assumptions!$B$27 -> 150000
A22: Fixed subtotal | B22: =B17+B19+B20+B21 -> 37150000 | C22: =C17+C19+C20+C21 -> 37150000 | D22: =D17+D19+D20+D21 -> 59150000
A23: RESULT
A24: Operating profit / (loss) — VND | B24: =B13-B22 -> -36125000 | C24: =C13-C22 -> -26900000 | D24: =D13-D22 -> 43350000
A25: Operating profit / (loss) — USD | B25: =B24/Assumptions!$B$30 -> -1389.4231 | C25: =C24/Assumptions!$B$30 -> -1034.6154 | D25: =D24/Assumptions!$B$30 -> 1667.3077
A26: Operating margin | B26: =IF(B6=0,0,B24/B6) -> -18.0625 | C26: =IF(C6=0,0,C24/C6) -> -1.345 | D26: =IF(D6=0,0,D24/D6) -> 0.21675
A27: Break-even trips / month* | B27: =IF(B14<=0,"n/a",B22/B14) -> 3624.3902 | C27: =IF(C14<=0,"n/a",C22/C14) -> 3624.3902 | D27: =IF(D14<=0,"n/a",D22/D14) -> 5770.7317

Sheet Assumptions
A1: ECOGO — Operational P&L Assumptions
A2: Blue = editable input. Salary/CAC figures are planning placeholders — replace with your real numbers.
A4: REVENUE
A5: Avg fare / booking | B5: 200000 | C5: VND | D5: Corridor dependent
A6: Platform fee | B6: 0.1 | C6: % of fare | D6: 10% taken from driver
A8: VARIABLE PER TRIP
A9: Technology cost / trip | B9: 2000 | C9: VND | D9: From the cloud + API cost model (Growth tier)
A10: Auto-match rate | B10: 0.75 | C10: fraction | D10: Share matched without a dispatcher
A11: Referred-trip share | B11: 0.15 | C11: fraction | D11: Share paying the 3-yr affiliate
A12: Affiliate rate | B12: 0.05 | C12: % of fare | D12: 5% to referring driver
A13: Marketing / incentive per trip | B13: 5000 | C13: VND | D13: Promos, passenger acquisition
A15: DRIVER ACQUISITION
A16: CAC per driver | B16: 150000 | C16: VND | D16: Cost to onboard one driver
A17: Trips per driver / month | B17: 10 | C17: trips | D17: Activity level
A18: Driver lifetime | B18: 12 | C18: months | D18: Before churn
A20: STAFFING & FIXED (VND / month)
A21: Dispatcher salary | B21: 12000000 | C21: VND/mo | D21: Loaded monthly cost per dispatcher
A22: Dispatch capacity | B22: 1500 | C22: trips/mo | D22: Dispatch-handled trips per dispatcher
A23: Min dispatchers | B23: 1 | C23: people | D23: Floor during operating hours
A24: Support salary | B24: 10000000 | C24: VND/mo | D24: Loaded monthly cost per agent
A25: Trips per support agent | B25: 5000 | C25: trips/mo | D25: Capacity per agent
A26: Overhead (office/admin/tools) | B26: 15000000 | C26: VND/mo | D26: Fixed regardless of volume
A27: Brandname upkeep | B27: 150000 | C27: VND/mo | D27: SMS brandname carriers
A29: FX
A30: FX rate | B30: 26000 | C30: VND/USD | D30: Approx mid-2026

Sheet Notes
A1: How to read this model
A3: This sits on top of the cloud + API cost model and adds the real cost centres that decide profitability.
A5: The shape of the business:
A6: - At Pilot volume it loses money by design — fixed staffing (a dispatcher must be on shift) and acquisition
A7: spend dwarf 100 trips of revenue. That is supply/demand seeding, not a broken model.
A8: - Break-even sits in the low thousands of trips/month: fixed monthly cost divided by contribution per trip.
A9: - At Scale it turns a healthy operating profit. The leverage is dispatch automation (a higher auto-match rate
A10: means fewer dispatchers per 1,000 trips) and fare/fee.
A12: The three levers that move profitability most:
A13: 1. Auto-match rate (Assumptions B10). Every point of automation reduces dispatcher headcount — the largest
A14: fixed cost. Investing in matching quality pays back directly here.
A15: 2. Average fare and fee (B5, B6). Contribution per trip scales linearly with both.
... A23: liability (model that in a dedicated finance model). All inputs are placeholders — replace with real figures.
